toolbox_utils/__init__.py
toolbox_utils/tsutils.py
toolbox_utils/readers/__init__.py
toolbox_utils/readers/hbn.py
toolbox_utils/readers/plotgen.py
toolbox_utils/readers/wdm.py
toolbox_utils-5.2.2.dist-info/licenses/LICENSE.txt
toolbox_utils-5.2.2.dist-info/METADATA
toolbox_utils-5.2.2.dist-info/WHEEL
toolbox_utils-5.2.2.dist-info/top_level.txt
toolbox_utils-5.2.2.dist-info/RECORD
