Metadata-Version: 2.4
Name: toolbox_utils
Version: 5.2.2
Summary: Python toolbox for common utilities
Author-email: Tim Cera <tim@cerazone.net>
License: BSD-3-Clause
Project-URL: documentation, https://timcera.bitbucket.io/toolbox_utils/docs/index.html#toolbox_utils-documentation
Project-URL: github, https://github.com/timcera/toolbox_utils
Project-URL: bitbucket, https://bitbucket.org/timcera/toolbox_utils/src/main/
Keywords: time-series,cli-app,aggregate,fill,filter
Classifier: Development Status :: 5 - Production/Stable
Classifier: Intended Audience :: Science/Research
Classifier: Intended Audience :: End Users/Desktop
Classifier: Intended Audience :: Developers
Classifier: Environment :: Console
Classifier: License :: OSI Approved :: BSD License
Classifier: Natural Language :: English
Classifier: Operating System :: OS Independent
Classifier: Programming Language :: Python :: 3 :: Only
Classifier: Programming Language :: Python :: 3.8
Classifier: Programming Language :: Python :: 3.9
Classifier: Programming Language :: Python :: 3.10
Classifier: Programming Language :: Python :: 3.11
Classifier: Programming Language :: Python :: 3.12
Classifier: Topic :: Scientific/Engineering :: Information Analysis
Classifier: Topic :: Scientific/Engineering
Classifier: Topic :: Software Development :: Libraries :: Python Modules
Requires-Python: >=3.8
License-File: LICENSE.txt
Requires-Dist: dateparser
Requires-Dist: numpy<2.0,>=1.20; python_version <= "3.9"
Requires-Dist: openpyxl
Requires-Dist: pandas[excel]
Requires-Dist: pint!=0.21.*,<0.22; python_version < "3.9"
Requires-Dist: pint-pandas
Requires-Dist: pydantic
Requires-Dist: scipy
Requires-Dist: tabulate
Dynamic: license-file
